micropython_mma8451/__init__.py
micropython_mma8451/i2c_helpers.py
micropython_mma8451/mma8451.py
micropython_mma8451-0.1.0.dist-info/LICENSE
micropython_mma8451-0.1.0.dist-info/METADATA
micropython_mma8451-0.1.0.dist-info/WHEEL
micropython_mma8451-0.1.0.dist-info/top_level.txt
micropython_mma8451-0.1.0.dist-info/RECORD
