Metadata-Version: 2.1
Name: micropython-mma8451
Version: 0.1.0
Summary: MicroPython module for the MMA8451 3 axis accelerometer
Author-email: JDM <xxyx@mailmeto.mozmail.com>
License: MIT
Project-URL: Homepage, https://github.com/jposada202020/MicroPython_MMA8451
Keywords: sensor,micropython,mma8451,micropython,driver,sensor,mma8451,mma8451q,acceleration,gravity,accelerometer
Classifier: Intended Audience :: Developers
Classifier: Topic :: Software Development :: Libraries
Classifier: Topic :: Software Development :: Embedded Systems
Classifier: Topic :: System :: Hardware
Classifier: License :: OSI Approved :: MIT License
Classifier: Programming Language :: Python :: Implementation :: MicroPython
License-File: LICENSE
